archicat/__init__.py
archicat/__main__.py
archicat/block.py
archicat/cli.py
archicat/components.py
archicat/error.py
archicat/extension.py
archicat/grammar.lark
archicat/parser.py
archicat/transformer.py
archicat/writer.py
archicat/blocks/arguments.py
archicat/blocks/control.py
archicat/blocks/data.py
archicat/blocks/event.py
archicat/blocks/looks.py
archicat/blocks/motion.py
archicat/blocks/operator.py
archicat/blocks/sensing.py
archicat/blocks/sound.py
archicat-0.1.0.dist-info/licenses/LICENSE
archicat-0.1.0.dist-info/METADATA
archicat-0.1.0.dist-info/WHEEL
archicat-0.1.0.dist-info/top_level.txt
archicat-0.1.0.dist-info/RECORD
