Metadata-Version: 2.4
Name: ArchiCat
Version: 0.1.0
Summary: Text based Scratch
Author: jasper-91
License-Expression: MIT
Project-URL: Homepage, https://github.com/jasper-91/ArchiCat
Project-URL: Issues, https://github.com/jasper-91/ArchiCat/issues
Classifier: Programming Language :: Python :: 3
Classifier: Operating System :: OS Independent
Requires-Python: >=3.12
License-File: LICENSE
Requires-Dist: lark==1.3.1
Requires-Dist: pydantic>=2.0.0
Requires-Dist: mutagen
Dynamic: license-file
